flask_jsonpages
